weekendwordle/__init__.py
weekendwordle/backend/atomic_ops.py
weekendwordle/backend/cache.py
weekendwordle/backend/classifier.py
weekendwordle/backend/cli_app.py
weekendwordle/backend/core.py
weekendwordle/backend/engine.py
weekendwordle/backend/helpers.py
weekendwordle/backend/messenger.py
weekendwordle/backend/tests.py
weekendwordle/config.json
weekendwordle/config.py
weekendwordle/config_loader.py
weekendwordle/data/en_US-large.txt
weekendwordle/data/original_answers.txt
weekendwordle/data/past_answers.txt
weekendwordle/data/pattern_matrix.npz
weekendwordle/data/trained_classifier.pkl
weekendwordle/data/valid_guesses.txt
weekendwordle/data/word_features.pkl
weekendwordle/gui/game/board_widget.py
weekendwordle/gui/game/confirm_screen.py
weekendwordle/gui/game/game_screen.py
weekendwordle/gui/game/game_screen.tcss
weekendwordle/gui/game/progress_widget.py
weekendwordle/gui/game/sidebar_widget.py
weekendwordle/gui/game/state.py
weekendwordle/gui/game/text_processors.py
weekendwordle/gui/loading/loading_screen.py
weekendwordle/gui/loading/loading_screen.tcss
weekendwordle/gui/settings/settings_screen.py
weekendwordle/gui/settings/settings_screen.tcss
weekendwordle/gui/setup/dynamic_list_widget.py
weekendwordle/gui/setup/filter_widget.py
weekendwordle/gui/setup/loading_widget.py
weekendwordle/gui/setup/setup_screen.py
weekendwordle/gui/setup/setup_screen.tcss
weekendwordle/gui/startup/startup_screen.py
weekendwordle/gui/startup/startup_screen.tcss
weekendwordle/gui/startup/transitional_loading_screen.py
weekendwordle/gui/wordle_app.py
weekendwordle-1.1.0.dist-info/licenses/LICENSES/ATOMIC_LICENSE
weekendwordle-1.1.0.dist-info/licenses/LICENSES/DEPENDENCY_LICENSES.md
weekendwordle-1.1.0.dist-info/licenses/LICENSES/HUNSPELL_LICENSE
weekendwordle-1.1.0.dist-info/WHEEL
weekendwordle-1.1.0.dist-info/entry_points.txt
weekendwordle-1.1.0.dist-info/METADATA
weekendwordle-1.1.0.dist-info/RECORD
