Metadata-Version: 2.4
Name: weekendwordle
Version: 1.1.0
Summary: WeekendWordle is a Python framework and TUI built to find near-optimal guesses for the modern, New York Times version of Wordle.
Author: Benjamin Saunders
Author-email: Benjamin Saunders <bengsaunders@gmail.com>
License-Expression: MIT
License-File: LICENSES/ATOMIC_LICENSE
License-File: LICENSES/DEPENDENCY_LICENSES.md
License-File: LICENSES/HUNSPELL_LICENSE
Requires-Dist: beautifulsoup4>=4.13.4
Requires-Dist: matplotlib>=3.10.3
Requires-Dist: nltk>=3.9.1
Requires-Dist: numba>=0.61.2
Requires-Dist: numpy>=2.2.6
Requires-Dist: pandas>=2.3.1
Requires-Dist: plotly>=6.2.0
Requires-Dist: pyfiglet>=1.0.4
Requires-Dist: pyperclip>=1.11.0
Requires-Dist: requests>=2.32.4
Requires-Dist: scikit-learn>=1.7
Requires-Dist: spacy>=3.8.7
Requires-Dist: textual>=5.3.0
Requires-Dist: textual-dev>=1.7.0
Requires-Dist: textual-pyfiglet>=1.1.0
Requires-Dist: tqdm>=4.67.1
Requires-Dist: wordfreq>=3.1.1
Requires-Python: >=3.13.5
Project-URL: Homepage, https://github.com/flyingfaller/WeekendWordleBot
